design.sv
// Code your design here
// Code your design here
module full_adder(
  input logic a,
  input logic b,
  input logic cin,
  output logic sum,
  output logic carry
);
  /*
  a b cin sum carry
  0 0 0   0   0
  0 0 1   1   0
  0 1 0	  1	  0
  0 1 1   0   1
  1 0 0   1   0
  1 0 1   0   1
  1 1 0   0   1
  1 1 1   1   1
  a_bar(b&&)c + a(b||c)
  */
  assign sum = a^b^cin;
  assign carry = (a&&b) || (b&&cin) || (a&&cin);
endmodule

testbench.sv
// Code your testbench here
// or browse Examples
module full_adder_tb;
  logic a;
  logic b;
  logic cin;
  logic sum;
  logic carry;
  
  logic sum_e;
  logic carry_e;
  
  full_adder full_adder_inst(.*);
  
  assign {carry_e, sum_e} = a + b + cin;
  
  function void compare(input logic a, input logic b, input logic cin, input logic sum, input logic sum_e, input logic carry, input logic carry_e);
    if ((sum == sum_e) && (carry == carry_e)) begin
      $display("print a is %0h b is %0h c is %0h sum is %0h carry is %0h", a, b, cin, sum, carry);
    end else begin
      $display("print a is %0h b is %0h c is %0h", a, b, cin);
      $display("print sum is %0h sum_e is %0h carry is %0h carry_e is %0h", sum, sum_e, carry, carry_e);
    end
  endfunction
      
  initial begin
    a = 0; b = 0; cin = 0;
    #1;
    repeat (50) begin
      {a, b, cin} = $random();
      compare(a, b, cin, sum, sum_e, carry , carry_e);
      #1;
    end   
  end

  initial begin
    $dumpfile("dump.vcd");
    $dumpvars;
  end
  
endmodule

dump.vcd
$date
	Sat Feb 25 06:40:07 2023
$end

$version
	Synopsys VCS version S-2021.09
$end

$timescale
	1ns
$end

$comment Csum: 1 82b10c3210685836 $end


$scope module full_adder_tb $end
$var reg 1 ! a $end
$var reg 1 " b $end
$var reg 1 # cin $end
$var reg 1 $ sum $end
$var reg 1 % carry $end
$var reg 1 & sum_e $end
$var reg 1 ' carry_e $end

$scope function compare $end
$var reg 1 ( a $end
$var reg 1 ) b $end
$var reg 1 * cin $end
$var reg 1 + sum $end
$var reg 1 , sum_e $end
$var reg 1 - carry $end
$var reg 1 . carry_e $end
$upscope $end


$scope module full_adder_inst $end
$var reg 1 ! a $end
$var reg 1 " b $end
$var reg 1 # cin $end
$var reg 1 $ sum $end
$var reg 1 % carry $end
$upscope $end

$upscope $end

$enddefinitions $end

#0
$dumpvars
0!
0"
0%
0'
0#
x(
x)
x-
x.
x*
x+
x,
0$
0&
$end
#1
1(
0)
0*
0+
0,
0-
0.
1!
1&
1$
#2
0(
1*
1+
1,
0!
1#
1&
1$
#4
1)
1"
0&
1'
1%
0$
#5
1(
0)
0+
0,
1-
1.
1!
0"
0&
0$
#8
0(
1)
0*
0!
1"
0#
1&
0'
0%
1$
#9
0)
1*
1+
1,
0-
0.
0"
1#
1&
#10
1(
1!
0&
1'
1%
0$
#11
1)
0*
0+
0,
1-
1.
1"
0#
0&
#12
0)
1*
0"
1#
0&
1'
1%
#14
0*
0#
1&
0'
0%
1$
#15
0(
1*
1+
1,
0-
0.
0!
1#
1&
1$
#16
1(
1)
0*
1!
1"
0#
0&
1'
1%
0$
#17
0)
1*
0+
0,
1-
1.
0"
1#
0&
1'
1%
#18
0(
1)
0*
0!
1"
0#
1&
0'
0%
1$
#19
1(
0)
1*
1+
1,
0-
0.
1!
0"
1#
0&
1'
1%
0$
#20
1)
0+
0,
1-
1.
1"
1&
1$
#21
0(
0*
1+
1,
0!
0#
1&
0%
1$
0'
#22
1(
1*
0-
0.
1!
1#
1&
1'
1%
1$
#23
0(
0*
1-
1.
0!
0#
1&
0%
1$
0'
#24
1(
0-
0.
1!
0&
1'
1%
0$
#25
0(
0)
0+
0,
1-
1.
0!
0"
0&
0'
0%
0$
#26
1(
1*
0-
0.
1!
1#
0&
1%
0$
1'
#27
0*
1-
1.
0#
1&
0'
0%
1$
#28
1*
1+
1,
0-
0.
1#
0&
1'
1%
0$
#29
0+
0,
1-
1.
#31
0(
1)
0!
1"
0&
1'
1%
0$
#32
0*
0#
1&
0'
0%
1$
#33
0)
1+
1,
0-
0.
0"
0&
0$
#34
0+
0,
#35
1)
1"
1&
1$
#36
1(
0)
1*
1+
1,
1!
0"
1#
0&
1'
1%
0$
#37
1)
0*
0+
0,
1-
1.
1"
0#
0&
#38
0(
1*
0!
1#
0&
1'
0$
#39
1(
0)
1!
0"
0&
0$
#40
0(
1)
0!
1"
0&
1'
1%
0$
#42
1(
0)
1!
0"
0&
0$
#43
0(
1)
0*
0!
1"
0#
1&
0'
0%
1$
#44
1(
1+
1,
0-
0.
1!
0&
1'
1%
0$
#45
0)
1*
0+
0,
1-
1.
0"
1#
0&
1'
1%
#46
1)
1"
1&
1$
#47
0(
1+
1,
0!
0&
0$
#48
0*
0+
0,
0#
1&
0'
0%
1$
#49
1+
1,
0-
0.
#50
1(
0)
1!
0"
1&
0'
1$
